adfmt/__init__.py
adfmt/enums.py
adfmt/format.py
adfmt/params.py
adfmt/units.py
adfmt-0.0.2.dist-info/LICENSE
adfmt-0.0.2.dist-info/METADATA
adfmt-0.0.2.dist-info/WHEEL
adfmt-0.0.2.dist-info/top_level.txt
adfmt-0.0.2.dist-info/RECORD
