Metadata-Version: 2.1
Name: adfmt
Version: 0.0.2
Summary: a simple format tool for apiDoc
Home-page: https://github.com/WangYue1993/adfmt
Author: Yue Wang
Author-email: wangyue930203@gmail.com
License: UNKNOWN
Platform: UNKNOWN
Classifier: Programming Language :: Python :: 3.5
Classifier: Programming Language :: Python :: 3.6
Classifier: Programming Language :: Python :: 3.7
Classifier: License :: OSI Approved :: MIT License
Classifier: Operating System :: OS Independent
Requires-Python: >=3.5
Requires-Dist: requests
